{
	"GDFCT": [
		{
			"entities": {
				"inputEntity": [
					{
						"entityId": "EN_CLIENTEQJ_451",
						"moduleId": "GDFCT",
						"related": false
					}
				],
				"outputEntity": [
				],
				"returnEntity": [
				]
			},
			"idBli": "BLI1616_bli_clientefactura_actualizar",
			"nameBli": "BLI_ClienteFactura_Actualizar"
		},
		{
			"entities": {
				"inputEntity": [
					{
						"entityId": "EN_CLIENTEQJ_451",
						"moduleId": "GDFCT",
						"related": false
					}
				],
				"outputEntity": [
				],
				"returnEntity": [
				]
			},
			"idBli": "BLI2733_bli_clientefactura_insertar",
			"nameBli": "BLI_ClienteFactura_Insertar"
		},
		{
			"entities": {
				"inputEntity": [
				],
				"outputEntity": [
				],
				"returnEntity": [
					{
						"entityId": "EN_CLIENTEQJ_451",
						"moduleId": "GDFCT",
						"related": false
					}
				]
			},
			"idBli": "BLI5074_bli_clientefactura_mostrar",
			"nameBli": "BLI_ClienteFactura_Mostrar"
		},
		{
			"entities": {
				"inputEntity": [
					{
						"entityId": "EN_CLIENTEQJ_451",
						"moduleId": "GDFCT",
						"related": false
					}
				],
				"outputEntity": [
				],
				"returnEntity": [
				]
			},
			"idBli": "BLI9415_bli_clientefactura_borrar",
			"nameBli": "BLI_ClienteFactura_Borrar"
		}
	]
}
